agent_kit/__init__.py
google_agent_kit-0.0.1.dist-info/LICENSE.txt
google_agent_kit-0.0.1.dist-info/METADATA
google_agent_kit-0.0.1.dist-info/WHEEL
google_agent_kit-0.0.1.dist-info/top_level.txt
google_agent_kit-0.0.1.dist-info/RECORD
