Metadata-Version: 2.2
Name: google-agent-kit
Version: 0.0.1
Summary: hello world
Author-email: hangfei <hangfei@google.com>
Project-URL: Homepage, https://www.google.com/
Project-URL: Bug Tracker, https://www.google.com/
Classifier: Programming Language :: Python :: 3
Classifier: License :: OSI Approved :: Apache Software License
Classifier: Operating System :: OS Independent
Requires-Python: >=3.8
License-File: LICENSE.txt
